rtl/ai_accelerator.v
module ai_accelerator(
    input clk,
    input start,
    input [31:0] vector_a,
    input [31:0] vector_b,
    output reg [31:0] result,
    output reg done
);

wire [7:0] a0 = vector_a[7:0];
wire [7:0] a1 = vector_a[15:8];
wire [7:0] a2 = vector_a[23:16];
wire [7:0] a3 = vector_a[31:24];

wire [7:0] b0 = vector_b[7:0];
wire [7:0] b1 = vector_b[15:8];
wire [7:0] b2 = vector_b[23:16];
wire [7:0] b3 = vector_b[31:24];

always @(posedge clk) begin

    if(start) begin
        result <= (a0*b0) + (a1*b1) + (a2*b2) + (a3*b3);
        done <= 1;
    end
    else begin
        done <= 0;
    end

end

endmodule

rtl/alu.v
module alu(
    input [31:0] a,
    input [31:0] b,
    input [3:0] alu_op,
    output reg [31:0] result
);

always @(*) begin
    case(alu_op)

        4'b0000: result = a + b;   // ADD
        4'b0001: result = a - b;   // SUB
        4'b0010: result = a & b;   // AND
        4'b0011: result = a | b;   // OR
        4'b0100: result = a ^ b;   // XOR

        default: result = 32'b0;

    endcase
end

endmodule

rtl/register_file.v
module register_file(
    input clk,
    input we,
    input [4:0] rs1,
    input [4:0] rs2,
    input [4:0] rd,
    input [31:0] wd,
    output [31:0] rd1,
    output [31:0] rd2
);

reg [31:0] registers [31:0];

assign rd1 = registers[rs1];
assign rd2 = registers[rs2];

always @(posedge clk) begin
    if (we && rd != 0)
        registers[rd] <= wd;
end

endmodule

rtl/riscv_core.v
module riscv_core(

    input clk,
    input start,

    input [4:0] rs1,
    input [4:0] rs2,
    input [4:0] rd,

    input [3:0] alu_op,
    input use_ai,

    input we,
    input [31:0] write_data,

    output [31:0] result_out

);

wire [31:0] reg1;
wire [31:0] reg2;

wire [31:0] alu_result;
wire [31:0] ai_result;

wire ai_done;

reg [31:0] final_result;


// Register File
register_file rf(
    .clk(clk),
    .we(we),
    .rs1(rs1),
    .rs2(rs2),
    .rd(rd),
    .wd(write_data),
    .rd1(reg1),
    .rd2(reg2)
);


// ALU
alu alu_unit(
    .a(reg1),
    .b(reg2),
    .alu_op(alu_op),
    .result(alu_result)
);


// AI Accelerator
ai_accelerator ai_unit(
    .clk(clk),
    .start(start),
    .vector_a(reg1),
    .vector_b(reg2),
    .result(ai_result),
    .done(ai_done)
);


// Result Selection
always @(*) begin

    if(use_ai)
        final_result = ai_result;
    else
        final_result = alu_result;

end

assign result_out = final_result;

endmodule

tb/tb_system.v
`timescale 1ns/1ps

module tb_system;

reg clk;
reg start;

reg [4:0] rs1;
reg [4:0] rs2;
reg [4:0] rd;

reg [3:0] alu_op;
reg use_ai;

reg we;
reg [31:0] write_data;

wire [31:0] result_out;


// Instantiate Processor
riscv_core cpu(

    .clk(clk),
    .start(start),

    .rs1(rs1),
    .rs2(rs2),
    .rd(rd),

    .alu_op(alu_op),
    .use_ai(use_ai),

    .we(we),
    .write_data(write_data),

    .result_out(result_out)

);


// Clock generation
always #5 clk = ~clk;


initial begin

    $dumpfile("system.vcd");
    $dumpvars(0,tb_system);

    clk = 0;
    start = 0;
    we = 0;

    // Write 10 to x1
    rd = 5'd1;
    write_data = 32'd10;
    we = 1;
    #10;

    // Write 5 to x2
    rd = 5'd2;
    write_data = 32'd5;
    #10;

    we = 0;

    // ALU ADD
    rs1 = 5'd1;
    rs2 = 5'd2;
    alu_op = 4'b0000;
    use_ai = 0;

    #20;

    // AI accelerator test
    start = 1;
    use_ai = 1;

    #20;

    start = 0;

    #20;

    $finish;

end

endmodule

simulation/system.vcd
$date
	Wed Mar 11 16:54:11 2026
$end
$version
	Icarus Verilog
$end
$timescale
	1ps
$end
$scope module tb_system $end
$var wire 32 ! result_out [31:0] $end
$var reg 4 " alu_op [3:0] $end
$var reg 1 # clk $end
$var reg 5 $ rd [4:0] $end
$var reg 5 % rs1 [4:0] $end
$var reg 5 & rs2 [4:0] $end
$var reg 1 ' start $end
$var reg 1 ( use_ai $end
$var reg 1 ) we $end
$var reg 32 * write_data [31:0] $end
$scope module cpu $end
$var wire 4 + alu_op [3:0] $end
$var wire 1 # clk $end
$var wire 5 , rd [4:0] $end
$var wire 32 - result_out [31:0] $end
$var wire 5 . rs1 [4:0] $end
$var wire 5 / rs2 [4:0] $end
$var wire 1 ' start $end
$var wire 1 ( use_ai $end
$var wire 1 ) we $end
$var wire 32 0 write_data [31:0] $end
$var wire 32 1 reg2 [31:0] $end
$var wire 32 2 reg1 [31:0] $end
$var wire 32 3 alu_result [31:0] $end
$var wire 32 4 ai_result [31:0] $end
$var wire 1 5 ai_done $end
$var reg 32 6 final_result [31:0] $end
$scope module ai_unit $end
$var wire 1 # clk $end
$var wire 1 ' start $end
$var wire 32 7 vector_b [31:0] $end
$var wire 32 8 vector_a [31:0] $end
$var wire 8 9 b3 [7:0] $end
$var wire 8 : b2 [7:0] $end
$var wire 8 ; b1 [7:0] $end
$var wire 8 < b0 [7:0] $end
$var wire 8 = a3 [7:0] $end
$var wire 8 > a2 [7:0] $end
$var wire 8 ? a1 [7:0] $end
$var wire 8 @ a0 [7:0] $end
$var reg 1 5 done $end
$var reg 32 A result [31:0] $end
$upscope $end
$scope module alu_unit $end
$var wire 4 B alu_op [3:0] $end
$var wire 32 C b [31:0] $end
$var wire 32 D a [31:0] $end
$var reg 32 E result [31:0] $end
$upscope $end
$scope module rf $end
$var wire 1 # clk $end
$var wire 5 F rd [4:0] $end
$var wire 32 G rd1 [31:0] $end
$var wire 32 H rd2 [31:0] $end
$var wire 5 I rs1 [4:0] $end
$var wire 5 J rs2 [4:0] $end
$var wire 32 K wd [31:0] $end
$var wire 1 ) we $end
$upscope $end
$upscope $end
$upscope $end
$enddefinitions $end
$comment Show the parameter values. $end
$dumpall
$end
#0
$dumpvars
b1010 K
bx J
bx I
bx H
bx G
b1 F
bx E
bx D
bx C
bx B
bx A
bx @
bx ?
bx >
bx =
bx <
bx ;
bx :
bx 9
bx 8
bx 7
bx 6
x5
bx 4
bx 3
bx 2
bx 1
b1010 0
bx /
bx .
bx -
b1 ,
bx +
b1010 *
1)
x(
0'
bx &
bx %
b1 $
0#
bx "
bx !
$end
#5000
05
1#
#10000
0#
b101 *
b101 0
b101 K
b10 $
b10 ,
b10 F
#15000
1#
#20000
b0 9
b0 :
b0 ;
b101 <
b0 =
b0 >
b0 ?
b1010 @
b1111 !
b1111 -
b1111 6
b1111 3
b1111 E
b101 1
b101 7
b101 C
b101 H
b1010 2
b1010 8
b1010 D
b1010 G
0#
0(
b0 "
b0 +
b0 B
b10 &
b10 /
b10 J
b1 %
b1 .
b1 I
0)
#25000
1#
#30000
0#
#35000
1#
#40000
bx !
bx -
bx 6
0#
1(
1'
#45000
b110010 !
b110010 -
b110010 6
15
b110010 4
b110010 A
1#
#50000
0#
#55000
1#
#60000
0#
0'
#65000
05
1#
